{
  "_id": "KPzalikum0000000",
  "name": "Zalikum",
  "type": "npc",
  "img": "icons/svg/mystery-man.svg",
  "system": {
    "abilities": {
      "str": {
        "value": 19,
        "proficient": 0,
        "bonuses": {
          "check": "",
          "save": ""
        },
        "max": null
      },
      "dex": {
        "value": 17,
        "proficient": 1,
        "bonuses": {
          "check": "",
          "save": ""
        },
        "max": null
      },
      "con": {
        "value": 21,
        "proficient": 0,
        "bonuses": {
          "check": "",
          "save": ""
        },
        "max": null
      },
      "int": {
        "value": 8,
        "proficient": 0,
        "bonuses": {
          "check": "",
          "save": ""
        },
        "max": null
      },
      "wis": {
        "value": 10,
        "proficient": 0,
        "bonuses": {
          "check": "",
          "save": ""
        },
        "max": null
      },
      "cha": {
        "value": 15,
        "proficient": 1,
        "bonuses": {
          "check": "",
          "save": ""
        },
        "max": null
      }
    },
    "attributes": {
      "ac": {
        "flat": 16,
        "calc": "flat"
      },
      "hp": {
        "value": 103,
        "max": 103,
        "temp": null,
        "tempmax": 0,
        "formula": "9d12+45"
      },
      "init": {
        "ability": "",
        "bonus": "0",
        "roll": {
          "min": null,
          "max": null,
          "mode": 0
        }
      },
      "movement": {
        "burrow": 0,
        "climb": 0,
        "fly": 80,
        "swim": 0,
        "walk": 20,
        "units": "ft",
        "hover": false
      },
      "attunement": {
        "max": 3
      },
      "senses": {
        "darkvision": 120,
        "blindsight": 0,
        "tremorsense": 0,
        "truesight": 0,
        "units": "ft",
        "special": ""
      },
      "spellcasting": "int",
      "exhaustion": 0,
      "concentration": {
        "ability": "",
        "roll": {
          "min": null,
          "max": null,
          "mode": 0
        },
        "bonuses": {
          "save": ""
        },
        "limit": 1
      },
      "hd": {
        "spent": 0
      },
      "death": {
        "ability": "",
        "roll": {
          "min": null,
          "max": null,
          "mode": 0
        },
        "success": 0,
        "failure": 0
      }
    },
    "details": {
      "biography": {
        "value": "<p><em>Waves of heat shimmer around a gigantic vulturelike creature made of sand. The sand crackles with dark energy, and the creature’s eyes burn with malign intelligence.</em><br>An enormous vulture forged from sand and malignant power, a zalikum is created by mages who capture souls of the damned and infuse them into the superheated sands of the desert.<br><strong>Abyssal Ties.</strong> The souls infusing a zalikum are from the Abyss. A zalikum’s creator can gather these souls from the Abyss themselves, but, more often, the creator makes a deal with a demon in exchange for the souls. Unfortunately for the creator, the demon usually hands over souls that aren’t the easiest to control, leading many creators to die at the talons of their zalikums. Such destruction frees the demon from its bonds, releasing it and the zalikum into the world.<br><strong>Innumerable Lives.</strong> The souls infusing the sand of the zalikum can reform it after it has been destroyed. This process consumes some of the power of the souls, forcing the zalikum to devour more souls to fuel further rebirths.<br><strong>Construct Nature.</strong> A zalikum doesn’t require air, food, drink, or sleep.<br>Content licensed under the @UUID[Compendium.koboldpressogl.koboldpressjournal.JournalEntry.KoboldPressOGL00.JournalEntryPage.KoboldPressOGLpg]{Open Game License}",
        "public": ""
      },
      "alignment": "neutral evil",
      "race": null,
      "type": {
        "value": "construct",
        "subtype": "",
        "swarm": "",
        "custom": ""
      },
      "environment": "",
      "cr": 7,
      "spellLevel": 0
    },
    "traits": {
      "size": "huge",
      "di": {
        "value": [
          "fire",
          "necrotic",
          "poison",
          "psychic"
        ],
        "bypasses": [],
        "custom": ""
      },
      "dr": {
        "value": [
          "bludgeoning",
          "piercing",
          "slashing"
        ],
        "bypasses": [
          "mgc"
        ],
        "custom": ""
      },
      "dv": {
        "value": [],
        "bypasses": [],
        "custom": ""
      },
      "ci": {
        "value": [
          "charmed",
          "exhaustion",
          "frightened",
          "paralyzed",
          "petrified",
          "poisoned"
        ]
      },
      "languages": {
        "value": [
          "custom"
        ],
        "custom": "understands the languages of its creator but can’t speak"
      },
      "dm": {
        "amount": {},
        "bypasses": []
      }
    },
    "currency": {
      "pp": 0,
      "gp": 0,
      "ep": 0,
      "sp": 0,
      "cp": 0
    },
    "skills": {
      "acr": {
        "value": 0,
        "ability": "dex",
        "bonuses": {
          "check": "",
          "passive": ""
        },
        "roll": {
          "min": null,
          "max": null,
          "mode": 0
        }
      },
      "ani": {
        "value": 0,
        "ability": "wis",
        "bonuses": {
          "check": "",
          "passive": ""
        },
        "roll": {
          "min": null,
          "max": null,
          "mode": 0
        }
      },
      "arc": {
        "value": 0,
        "ability": "int",
        "bonuses": {
          "check": "",
          "passive": ""
        },
        "roll": {
          "min": null,
          "max": null,
          "mode": 0
        }
      },
      "ath": {
        "value": 0,
        "ability": "str",
        "bonuses": {
          "check": "",
          "passive": ""
        },
        "roll": {
          "min": null,
          "max": null,
          "mode": 0
        }
      },
      "dec": {
        "value": 0,
        "ability": "cha",
        "bonuses": {
          "check": "",
          "passive": ""
        },
        "roll": {
          "min": null,
          "max": null,
          "mode": 0
        }
      },
      "his": {
        "value": 0,
        "ability": "int",
        "bonuses": {
          "check": "",
          "passive": ""
        },
        "roll": {
          "min": null,
          "max": null,
          "mode": 0
        }
      },
      "ins": {
        "value": 0,
        "ability": "wis",
        "bonuses": {
          "check": "",
          "passive": ""
        },
        "roll": {
          "min": null,
          "max": null,
          "mode": 0
        }
      },
      "itm": {
        "value": 0,
        "ability": "cha",
        "bonuses": {
          "check": "",
          "passive": ""
        },
        "roll": {
          "min": null,
          "max": null,
          "mode": 0
        }
      },
      "inv": {
        "value": 0,
        "ability": "int",
        "bonuses": {
          "check": "",
          "passive": ""
        },
        "roll": {
          "min": null,
          "max": null,
          "mode": 0
        }
      },
      "med": {
        "value": 0,
        "ability": "wis",
        "bonuses": {
          "check": "",
          "passive": ""
        },
        "roll": {
          "min": null,
          "max": null,
          "mode": 0
        }
      },
      "nat": {
        "value": 0,
        "ability": "int",
        "bonuses": {
          "check": "",
          "passive": ""
        },
        "roll": {
          "min": null,
          "max": null,
          "mode": 0
        }
      },
      "prc": {
        "value": 1,
        "ability": "wis",
        "bonuses": {
          "check": "",
          "passive": ""
        },
        "roll": {
          "min": null,
          "max": null,
          "mode": 0
        }
      },
      "prf": {
        "value": 0,
        "ability": "cha",
        "bonuses": {
          "check": "",
          "passive": ""
        },
        "roll": {
          "min": null,
          "max": null,
          "mode": 0
        }
      },
      "per": {
        "value": 0,
        "ability": "cha",
        "bonuses": {
          "check": "",
          "passive": ""
        },
        "roll": {
          "min": null,
          "max": null,
          "mode": 0
        }
      },
      "rel": {
        "value": 0,
        "ability": "int",
        "bonuses": {
          "check": "",
          "passive": ""
        },
        "roll": {
          "min": null,
          "max": null,
          "mode": 0
        }
      },
      "slt": {
        "value": 0,
        "ability": "dex",
        "bonuses": {
          "check": "",
          "passive": ""
        },
        "roll": {
          "min": null,
          "max": null,
          "mode": 0
        }
      },
      "ste": {
        "value": 0,
        "ability": "dex",
        "bonuses": {
          "check": "",
          "passive": ""
        },
        "roll": {
          "min": null,
          "max": null,
          "mode": 0
        }
      },
      "sur": {
        "value": 0,
        "ability": "wis",
        "bonuses": {
          "check": "",
          "passive": ""
        },
        "roll": {
          "min": null,
          "max": null,
          "mode": 0
        }
      }
    },
    "spells": {
      "spell1": {},
      "spell2": {},
      "spell3": {},
      "spell4": {},
      "spell5": {},
      "spell6": {},
      "spell7": {},
      "spell8": {},
      "spell9": {},
      "pact": {
        "value": 0,
        "override": null
      },
      "spell0": {
        "value": 0,
        "override": null
      }
    },
    "bonuses": {
      "mwak": {
        "attack": "",
        "damage": ""
      },
      "rwak": {
        "attack": "",
        "damage": ""
      },
      "msak": {
        "attack": "",
        "damage": ""
      },
      "rsak": {
        "attack": "",
        "damage": ""
      },
      "abilities": {
        "check": "",
        "save": "",
        "skill": ""
      },
      "spell": {
        "dc": ""
      }
    },
    "resources": {
      "legact": {
        "value": 0,
        "max": 0
      },
      "legres": {
        "value": 0,
        "max": 0
      },
      "lair": {
        "value": false,
        "initiative": null
      }
    },
    "tools": {},
    "source": {
      "custom": "",
      "book": "ToB2",
      "page": "",
      "license": "OGL-1.0a",
      "revision": 1,
      "rules": "2014"
    }
  },
  "prototypeToken": {
    "name": "Zalikum",
    "width": 3,
    "height": 3,
    "displayName": 20,
    "actorLink": false,
    "lockRotation": true,
    "rotation": 0,
    "disposition": -1,
    "displayBars": 40,
    "bar1": {
      "attribute": "attributes.hp"
    },
    "bar2": {
      "attribute": null
    },
    "flags": {},
    "randomImg": false,
    "alpha": 1,
    "light": {
      "alpha": 1,
      "angle": 360,
      "bright": 0,
      "coloration": 1,
      "dim": 0,
      "luminosity": 0.5,
      "saturation": 0,
      "contrast": 0,
      "shadows": 0,
      "animation": {
        "speed": 5,
        "intensity": 5,
        "type": null,
        "reverse": false
      },
      "darkness": {
        "min": 0,
        "max": 1
      },
      "attenuation": 0.5,
      "color": null,
      "negative": false,
      "priority": 0
    },
    "texture": {
      "src": null,
      "tint": "#ffffff",
      "scaleX": 1,
      "scaleY": 1,
      "offsetX": 0,
      "offsetY": 0,
      "rotation": 0,
      "anchorX": 0.5,
      "anchorY": 0.5,
      "fit": "contain",
      "alphaThreshold": 0.75
    },
    "sight": {
      "angle": 360,
      "enabled": false,
      "range": 120,
      "brightness": 0,
      "visionMode": "darkvision",
      "color": null,
      "attenuation": 0.1,
      "saturation": 0,
      "contrast": 0
    },
    "detectionModes": [],
    "appendNumber": false,
    "prependAdjective": false,
    "hexagonalShape": 1,
    "occludable": {
      "radius": 0
    },
    "ring": {
      "enabled": false,
      "colors": {
        "ring": null,
        "background": null
      },
      "effects": 1,
      "subject": {
        "scale": 1,
        "texture": null
      }
    }
  },
  "items": [
    {
      "_id": "0000000000000001",
      "name": "Flyby",
      "type": "feat",
      "img": "icons/creatures/mammals/bats-movement-flying-purple.webp",
      "system": {
        "description": {
          "value": "<p>The zalikum doesn’t provoke opportunity attacks when it flies out of an enemy’s reach.",
          "chat": ""
        },
        "source": {
          "custom": "",
          "book": "",
          "page": "",
          "license": "OGL-1.0a",
          "rules": "2014",
          "revision": 1
        },
        "uses": {
          "max": "",
          "spent": 0,
          "recovery": []
        },
        "type": {
          "value": "monster",
          "subtype": ""
        },
        "properties": [
          "trait"
        ],
        "activities": {},
        "identifier": "flyby"
      },
      "effects": [],
      "folder": null,
      "sort": 1,
      "ownership": {
        "default": 0
      },
      "flags": {},
      "_key": "!actors.items!KPzalikum0000000.0000000000000001"
    },
    {
      "_id": "0000000000000002",
      "name": "Ghastly Heated Body",
      "type": "feat",
      "img": "systems/dnd5e/icons/svg/items/feature.svg",
      "system": {
        "description": {
          "value": "<p>A creature that touches the zalikum or hits it with a melee attack while within 5 feet of it takes 3 (1d6) fire damage and 3 (1d6) necrotic damage.",
          "chat": ""
        },
        "source": {
          "custom": "",
          "book": "",
          "page": "",
          "license": "OGL-1.0a",
          "rules": "2014",
          "revision": 1
        },
        "uses": {
          "max": "",
          "spent": 0,
          "recovery": []
        },
        "type": {
          "value": "monster",
          "subtype": ""
        },
        "properties": [
          "trait"
        ],
        "activities": {},
        "identifier": "ghastly-heated-body"
      },
      "effects": [],
      "folder": null,
      "sort": 2,
      "ownership": {
        "default": 0
      },
      "flags": {},
      "_key": "!actors.items!KPzalikum0000000.0000000000000002"
    },
    {
      "_id": "0000000000000003",
      "name": "Rejuvenation",
      "type": "feat",
      "img": "icons/magic/control/debuff-energy-hold-levitate-green.webp",
      "system": {
        "description": {
          "value": "<p>The zalikum can store the souls of up to 3 victims inside it at one time. If it has at least 1 soul, a destroyed zalikum gains a new body in 1d10 days, regaining all its hp and becoming active again. The new body appears within 5 feet of its sandy remains. If its sandy remains are soaked with holy water and buried in consecrated ground, its trapped souls are freed, and the zalikum can’t rejuvenate.",
          "chat": ""
        },
        "source": {
          "custom": "",
          "book": "",
          "page": "",
          "license": "OGL-1.0a",
          "rules": "2014",
          "revision": 1
        },
        "uses": {
          "max": "",
          "spent": 0,
          "recovery": []
        },
        "type": {
          "value": "monster",
          "subtype": ""
        },
        "properties": [
          "trait"
        ],
        "activities": {},
        "identifier": "rejuvenation"
      },
      "effects": [],
      "folder": null,
      "sort": 3,
      "ownership": {
        "default": 0
      },
      "flags": {},
      "_key": "!actors.items!KPzalikum0000000.0000000000000003"
    },
    {
      "_id": "0000000000000004",
      "name": "Multiattack",
      "type": "feat",
      "img": "icons/skills/melee/blade-tips-triple-steel.webp",
      "system": {
        "description": {
          "value": "<p>The zalikum makes one beak attack and one talon attack.",
          "chat": ""
        },
        "source": {
          "custom": "",
          "book": "",
          "page": "",
          "license": "OGL-1.0a",
          "rules": "2014",
          "revision": 1
        },
        "uses": {
          "max": "",
          "spent": 0,
          "recovery": []
        },
        "type": {
          "value": "monster",
          "subtype": ""
        },
        "properties": [],
        "activities": {
          "KPOGLactivityUtl": {
            "_id": "KPOGLactivityUtl",
            "type": "utility",
            "activation": {
              "type": "action",
              "value": 1,
              "condition": "",
              "override": false
            },
            "consumption": {
              "targets": [],
              "scaling": {
                "allowed": false,
                "max": ""
              },
              "spellSlot": true
            },
            "description": {
              "chatFlavor": ""
            },
            "duration": {
              "concentration": false,
              "value": "",
              "units": "inst",
              "special": "",
              "override": false
            },
            "effects": [],
            "target": {
              "template": {
                "count": "",
                "contiguous": false,
                "type": "",
                "size": "",
                "width": "",
                "height": "",
                "units": ""
              },
              "affects": {
                "count": "",
                "type": "",
                "choice": false,
                "special": ""
              },
              "prompt": true,
              "override": false
            },
            "uses": {
              "spent": 0,
              "max": "",
              "recovery": []
            },
            "roll": {
              "formula": "",
              "name": "",
              "prompt": false,
              "visible": false
            },
            "sort": 0
          }
        },
        "identifier": "multiattack"
      },
      "effects": [],
      "folder": null,
      "sort": 4,
      "ownership": {
        "default": 0
      },
      "flags": {},
      "_key": "!actors.items!KPzalikum0000000.0000000000000004"
    },
    {
      "_id": "0000000000000005",
      "name": "Beak",
      "type": "weapon",
      "img": "icons/skills/wounds/bone-broken-tooth-fang-red.webp",
      "system": {
        "description": {
          "value": "<p>Melee Weapon Attack: +7 to hit, reach 10 ft., one target. Hit: 13 (2d8 + 4) piercing damage plus 3 (1d6) fire damage and 3 (1d6) necrotic damage. If a creature is slain by this attack, its body crumbles to sand, and the zalikum stores its soul. The creature can be restored to life only if the zalikum is destroyed and can’t rejuvenate (see the Rejuvenation trait).",
          "chat": ""
        },
        "source": {
          "custom": "",
          "book": "ToB2",
          "page": "",
          "license": "OGL-1.0a",
          "revision": 1,
          "rules": "2014"
        },
        "type": {
          "value": "natural",
          "baseItem": ""
        },
        "identifier": "",
        "attunement": "",
        "equipped": true,
        "identified": true,
        "cover": null,
        "range": {
          "value": null,
          "long": null,
          "units": "ft",
          "reach": "10"
        },
        "uses": {
          "max": "",
          "recovery": [],
          "spent": 0
        },
        "damage": {
          "versatile": {
            "number": null,
            "denomination": null,
            "bonus": "",
            "types": [],
            "custom": {
              "enabled": false,
              "formula": ""
            },
            "scaling": {
              "mode": "",
              "number": null,
              "formula": ""
            }
          },
          "base": {
            "number": 2,
            "denomination": 8,
            "bonus": "",
            "types": [
              "piercing"
            ],
            "custom": {
              "enabled": false,
              "formula": ""
            },
            "scaling": {
              "mode": "",
              "number": null,
              "formula": ""
            }
          }
        },
        "properties": [],
        "proficient": 1,
        "unidentified": {
          "description": ""
        },
        "container": null,
        "crewed": false,
        "activities": {
          "KPOGLactivityAtk": {
            "_id": "KPOGLactivityAtk",
            "type": "attack",
            "activation": {
              "type": "action",
              "value": 1,
              "condition": "",
              "override": false
            },
            "consumption": {
              "targets": [],
              "scaling": {
                "allowed": false,
                "max": ""
              },
              "spellSlot": true
            },
            "description": {
              "chatFlavor": ""
            },
            "duration": {
              "concentration": false,
              "value": "",
              "units": "",
              "special": "",
              "override": false
            },
            "effects": [],
            "range": {
              "value": "10",
              "units": "ft",
              "special": "",
              "override": false
            },
            "target": {
              "template": {
                "count": "",
                "contiguous": false,
                "type": "",
                "size": "",
                "width": "",
                "height": "",
                "units": ""
              },
              "affects": {
                "count": "",
                "type": "",
                "choice": false,
                "special": ""
              },
              "prompt": true,
              "override": false
            },
            "uses": {
              "spent": 0,
              "max": "",
              "recovery": []
            },
            "attack": {
              "ability": "str",
              "bonus": "0",
              "critical": {
                "threshold": null
              },
              "flat": false,
              "type": {
                "value": "melee",
                "classification": "weapon"
              }
            },
            "damage": {
              "critical": {
                "bonus": ""
              },
              "includeBase": true,
              "parts": [
                {
                  "number": 1,
                  "denomination": 6,
                  "bonus": "",
                  "types": [
                    "fire"
                  ],
                  "custom": {
                    "enabled": false,
                    "formula": ""
                  },
                  "scaling": {
                    "mode": "",
                    "number": null,
                    "formula": ""
                  }
                }
              ]
            },
            "sort": 0
          }
        },
        "attuned": false,
        "ammunition": {},
        "magicalBonus": null
      },
      "effects": [],
      "folder": null,
      "sort": 5,
      "owndership": {
        "default": 0
      },
      "flags": {},
      "_key": "!actors.items!KPzalikum0000000.0000000000000005"
    },
    {
      "_id": "0000000000000006",
      "name": "Talon",
      "type": "weapon",
      "img": "systems/dnd5e/icons/svg/items/weapon.svg",
      "system": {
        "description": {
          "value": "<p>Melee Weapon Attack: +7 to hit, reach 5 ft., one target. Hit: 11 (2d6 + 4) slashing damage plus 3 (1d6) fire damage and 3 (1d6) necrotic damage.",
          "chat": ""
        },
        "source": {
          "custom": "",
          "book": "ToB2",
          "page": "",
          "license": "OGL-1.0a",
          "revision": 1,
          "rules": "2014"
        },
        "type": {
          "value": "natural",
          "baseItem": ""
        },
        "identifier": "",
        "attunement": "",
        "equipped": true,
        "identified": true,
        "cover": null,
        "range": {
          "value": null,
          "long": null,
          "units": "ft",
          "reach": "5"
        },
        "uses": {
          "max": "",
          "recovery": [],
          "spent": 0
        },
        "damage": {
          "versatile": {
            "number": null,
            "denomination": null,
            "bonus": "",
            "types": [],
            "custom": {
              "enabled": false,
              "formula": ""
            },
            "scaling": {
              "mode": "",
              "number": null,
              "formula": ""
            }
          },
          "base": {
            "number": 2,
            "denomination": 6,
            "bonus": "",
            "types": [
              "slashing"
            ],
            "custom": {
              "enabled": false,
              "formula": ""
            },
            "scaling": {
              "mode": "",
              "number": null,
              "formula": ""
            }
          }
        },
        "properties": [],
        "proficient": 1,
        "unidentified": {
          "description": ""
        },
        "container": null,
        "crewed": false,
        "activities": {
          "KPOGLactivityAtk": {
            "_id": "KPOGLactivityAtk",
            "type": "attack",
            "activation": {
              "type": "action",
              "value": 1,
              "condition": "",
              "override": false
            },
            "consumption": {
              "targets": [],
              "scaling": {
                "allowed": false,
                "max": ""
              },
              "spellSlot": true
            },
            "description": {
              "chatFlavor": ""
            },
            "duration": {
              "concentration": false,
              "value": "",
              "units": "",
              "special": "",
              "override": false
            },
            "effects": [],
            "range": {
              "value": "5",
              "units": "ft",
              "special": "",
              "override": false
            },
            "target": {
              "template": {
                "count": "",
                "contiguous": false,
                "type": "",
                "size": "",
                "width": "",
                "height": "",
                "units": ""
              },
              "affects": {
                "count": "",
                "type": "",
                "choice": false,
                "special": ""
              },
              "prompt": true,
              "override": false
            },
            "uses": {
              "spent": 0,
              "max": "",
              "recovery": []
            },
            "attack": {
              "ability": "str",
              "bonus": "0",
              "critical": {
                "threshold": null
              },
              "flat": false,
              "type": {
                "value": "melee",
                "classification": "weapon"
              }
            },
            "damage": {
              "critical": {
                "bonus": ""
              },
              "includeBase": true,
              "parts": [
                {
                  "number": 1,
                  "denomination": 6,
                  "bonus": "",
                  "types": [
                    "fire"
                  ],
                  "custom": {
                    "enabled": false,
                    "formula": ""
                  },
                  "scaling": {
                    "mode": "",
                    "number": null,
                    "formula": ""
                  }
                }
              ]
            },
            "sort": 0
          }
        },
        "attuned": false,
        "ammunition": {},
        "magicalBonus": null
      },
      "effects": [],
      "folder": null,
      "sort": 6,
      "owndership": {
        "default": 0
      },
      "flags": {},
      "_key": "!actors.items!KPzalikum0000000.0000000000000006"
    },
    {
      "_id": "0000000000000007",
      "name": "Death-infused Desert Breath",
      "type": "feat",
      "img": "systems/dnd5e/icons/svg/items/feature.svg",
      "system": {
        "description": {
          "value": "<p>The zalikum exhales superheated sand infused with the power of damned souls in a 30-foot cone. Each creature in the area must make a DC 16 Dexterity saving throw, taking 14 (4d6) fire damage and 14 (4d6) necrotic damage on a failed save, or half as much damage on a successful one. If a creature’s saving throw fails by 5 or more, the creature also suffers one level of exhaustion.",
          "chat": ""
        },
        "source": {
          "custom": "",
          "book": "",
          "page": "",
          "license": "OGL-1.0a",
          "rules": "2014",
          "revision": 1
        },
        "uses": {
          "max": "",
          "spent": 0,
          "recovery": []
        },
        "type": {
          "value": "monster",
          "subtype": ""
        },
        "properties": [],
        "activities": {
          "KPOGLactivitySav": {
            "_id": "KPOGLactivitySav",
            "type": "save",
            "activation": {
              "type": "action",
              "value": 1,
              "condition": "",
              "override": false
            },
            "consumption": {
              "targets": [],
              "scaling": {
                "allowed": false,
                "max": ""
              },
              "spellSlot": true
            },
            "description": {
              "chatFlavor": ""
            },
            "duration": {
              "concentration": false,
              "value": "",
              "units": "inst",
              "special": "",
              "override": false
            },
            "effects": [],
            "range": {
              "value": "",
              "units": "",
              "special": "",
              "override": false
            },
            "target": {
              "affects": {
                "choice": false
              },
              "template": {
                "units": "ft",
                "type": "cone",
                "size": "30",
                "contiguous": false
              }
            },
            "damage": {
              "parts": [
                {
                  "number": 4,
                  "denomination": 6,
                  "bonus": "",
                  "types": [
                    "fire"
                  ],
                  "custom": {
                    "enabled": false,
                    "formula": ""
                  },
                  "scaling": {
                    "mode": "",
                    "number": null,
                    "formula": ""
                  }
                }
              ],
              "onSave": "half"
            },
            "save": {
              "ability": [
                "dex"
              ],
              "dc": {
                "calculation": "",
                "formula": "16"
              }
            },
            "uses": {
              "spent": 0,
              "max": "",
              "recovery": []
            },
            "sort": 0
          }
        },
        "identifier": "death-infused-desert-breath"
      },
      "effects": [],
      "folder": null,
      "sort": 7,
      "ownership": {
        "default": 0
      },
      "flags": {},
      "_key": "!actors.items!KPzalikum0000000.0000000000000007"
    },
    {
      "_id": "0000000000000008",
      "name": "Natural Armor",
      "permission": {
        "default": 0,
        "OtBWCJNgwo0VVuQx": 3
      },
      "type": "equipment",
      "data": {
        "description": {
          "value": "",
          "chat": "",
          "unidentified": ""
        },
        "source": "",
        "equipped": true,
        "rarity": "",
        "identified": true,
        "activation": {
          "type": "",
          "cost": 0,
          "condition": ""
        },
        "duration": {
          "value": null,
          "units": ""
        },
        "target": {
          "value": null,
          "width": null,
          "units": "",
          "type": ""
        },
        "range": {
          "value": null,
          "long": null,
          "units": ""
        },
        "uses": {
          "value": 0,
          "max": 0,
          "per": null
        },
        "consume": {
          "type": "",
          "target": null,
          "amount": null
        },
        "ability": null,
        "actionType": "",
        "attackBonus": 0,
        "chatFlavor": "",
        "critical": null,
        "damage": {
          "parts": [],
          "versatile": ""
        },
        "formula": "",
        "save": {
          "ability": "",
          "dc": null,
          "scaling": "spell"
        },
        "armor": {
          "value": 16,
          "type": "natural",
          "dex": null
        },
        "hp": {
          "value": 0,
          "max": 0,
          "dt": null,
          "conditions": ""
        },
        "speed": {
          "value": null,
          "conditions": ""
        },
        "strength": 0,
        "stealth": false,
        "proficient": true
      },
      "folder": "",
      "sort": 100001,
      "flags": {},
      "img": "icons/svg/mystery-man.svg",
      "effects": [],
      "_key": "!actors.items!KPzalikum0000000.0000000000000008"
    }
  ],
  "sort": 1711,
  "flags": {},
  "effects": [],
  "_key": "!actors!KPzalikum0000000"
}
