{
  "name": "Fanged Mask",
  "_id": "KPfangedmask0000",
  "effects": [],
  "folder": null,
  "flags": {},
  "type": "equipment",
  "img": "icons/equipment/back/cloak-brown-collared-fur-white-tied.webp",
  "system": {
    "description": {
      "value": "<p><em>Wondrous item, uncommon (requires attunement)</em><br>This tribal mask is made of wood and adorned with animal fangs. Once donned, it melds to your face and causes fangs to sprout from your mouth. While wearing this mask, your bite is a natural melee weapon, which you can use to make unarmed strikes. When you hit with it, your bite deals piercing damage equal to 1d4 + your Strength modifier, instead of the bludgeoning damage normal for an unarmed strike. If you already have a bite attack when you don and attune to this mask, your bite attack’s damage dice double (for example, 1d4 becomes 2d4).<br>Content licensed under the @UUID[Compendium.koboldpressogl.koboldpressjournal.JournalEntry.KoboldPressOGL00.JournalEntryPage.KoboldPressOGLpg]{Open Game License}",
      "chat": ""
    },
    "identifier": "fanged-mask",
    "source": {
      "book": "VoM",
      "revision": 1,
      "rules": "2014"
    },
    "identified": true,
    "unidentified": {
      "description": ""
    },
    "container": null,
    "quantity": 1,
    "weight": {
      "value": 0,
      "units": "lb"
    },
    "price": {
      "value": 0,
      "denomination": "gp"
    },
    "attunement": "",
    "type": {
      "value": "clothing",
      "subtype": ""
    },
    "properties": [
      "mgc"
    ],
    "rarity": "uncommon"
  },
  "_key": "!items!KPfangedmask0000"
}
