{
  "name": "Staff of the World Ash",
  "_id": "KPstaffoftheworl",
  "effects": [],
  "folder": null,
  "flags": {},
  "type": "weapon",
  "img": "icons/weapons/staves/staff-simple-carved.webp",
  "system": {
    "description": {
      "value": "<p><em>Staff, rare (requires attunement by a bard, druid, ranger, or wizard)</em><br>This staff of silvery-grey ash has been cut from a branch of Yggdrasil and is carved with the Eiwaz rune. Ravenfolk and other dwellers in the World Ash create these staffs to more easily travel its planar pathways.<br>You can perfectly recall any path you have traveled while holding this staff.<br>By striking the staff on the ground or against a branch of Yggdrasil as a bonus action, you can transform it into a <em>@UUID[Compendium.dnd5e.spells.Item.VzgFzcmocr1X1cp4]{shillelagh}</em> (as the spell) for 1 minute.<br>The staff has 10 charges and regains 1d6 + 4 expended charges daily at dawn. If you expend the last charge, roll a d20. On a 1, the staff loses its properties and becomes a nonmagical quarterstaff.<br><em><strong>Spells.</strong></em> You can use an action to expend one or more of the staff’s charges to cast one of the following spells: <em>@UUID[Compendium.dnd5e.spells.Item.a3XtAO5n2GrqiAh5]{create or destroy water}</em> (1 charge), <em>@UUID[Compendium.dnd5e.spells.Item.da0a1t2FqaTjRZGT]{freedom of movement}</em> (4 charges), <em>@UUID[Compendium.koboldpressogl.koboldpressspells.Item.KPlocateredporta]{locate Red Portal}</em> (3 charges), <em>@UUID[Compendium.dnd5e.spells.Item.Kn7K5PtYUJAKZTTp]{purify food and drink}</em> (1 charge), <em>@UUID[Compendium.dnd5e.spells.Item.2VXGS206tuChoeXy]{speak with plants}</em> (3 charges).<br>Content licensed under the @UUID[Compendium.koboldpressogl.koboldpressjournal.JournalEntry.KoboldPressOGL00.JournalEntryPage.KoboldPressOGLpg]{Open Game License}",
      "chat": ""
    },
    "identifier": "staff-of-the-world-ash",
    "source": {
      "book": "WG",
      "revision": 1,
      "rules": "2014"
    },
    "identified": true,
    "unidentified": {
      "description": ""
    },
    "container": null,
    "quantity": 1,
    "weight": {
      "value": 0,
      "units": "lb"
    },
    "price": {
      "value": 0,
      "denomination": "gp"
    },
    "type": {
      "value": "simpleM",
      "baseItem": "quarterstaff"
    },
    "damage": {
      "base": {
        "types": [],
        "custom": {
          "enabled": false
        },
        "scaling": {
          "number": 1
        }
      },
      "versatile": {
        "types": [],
        "custom": {
          "enabled": false
        },
        "scaling": {
          "number": 1
        }
      }
    },
    "properties": [
      "mgc"
    ],
    "uses": {
      "spent": 0,
      "max": "10",
      "recovery": [
        {
          "period": "dawn",
          "formula": "1d6 + 4",
          "type": "formula"
        }
      ]
    },
    "rarity": "rare"
  },
  "_key": "!items!KPstaffoftheworl"
}
